milestone3/__init__.py
milestone3/leos_tasks.py
milestone3-0.0.31.dist-info/METADATA
milestone3-0.0.31.dist-info/WHEEL
milestone3-0.0.31.dist-info/licenses/LICENSE
milestone3-0.0.31.dist-info/RECORD
