Metadata-Version: 2.1
Name: milestone3
Version: 0.0.31
Summary: Ingest a SODA object into a pandas.df
Author-email: Leo Irakliotis <leo@cs.luc.edu>
License-File: LICENSE
Classifier: License :: OSI Approved :: MIT License
Classifier: Operating System :: OS Independent
Classifier: Programming Language :: Python :: 3
Requires-Python: >=3.8
